riseup/__init__.py
riseup/riseup.py
Riseup_Mail-0.1.dist-info/LICENSE
Riseup_Mail-0.1.dist-info/METADATA
Riseup_Mail-0.1.dist-info/WHEEL
Riseup_Mail-0.1.dist-info/top_level.txt
Riseup_Mail-0.1.dist-info/RECORD
