Metadata-Version: 2.1
Name: Riseup-Mail
Version: 0.1
Summary: Writing and Reading Riseup Mails
Home-page: https://github.com/m1ghtfr3e/RiseupMail
Author: m1ghtfr3e
License: UNKNOWN
Platform: UNKNOWN
Classifier: Development Status :: 2 - Pre-Alpha
Classifier: Programming Language :: Python :: 3
Classifier: Programming Language :: Unix Shell
Classifier: Topic :: Communications :: Email
Classifier: Topic :: Security
Classifier: Operating System :: OS Independent
